[
  {
    "title": "Artificial Intelligence & Machine Learning: Emerging Legal and Self-Regulatory Considerations",
    "summary": "ABA Antitrust Section report shaping global guidance on competition and AI governance.",
    "url": "https://www.macmillankeck.pro/wp-content/uploads/2022/03/ABA-Antitrust-AI-report-Part-1-093019_Rory.pdf",
    "year": "2019"
  },
  {
    "title": "Competition for-the-Market",
    "summary": "OECD Global Forum on Competition presentation on auction design and market access.",
    "url": "https://www.macmillankeck.pro/wp-content/uploads/2022/11/Macmillan-OECD-Competition-for-the-market-2019.pdf",
    "year": "2019"
  },
  {
    "title": "Regulation of Cross-Border Non-Bank Remittances",
    "summary": "World Bank study of Philippines–Malaysia remittance corridors and enabling regulation.",
    "url": "https://www.macmillankeck.pro/wp-content/uploads/2022/07/remittances_report_final_for_sharing.pdf",
    "year": "2019"
  },
  {
    "title": "Driving Financial Inclusion through Mobile Financial Services in Bangladesh",
    "summary": "Case study on enabling interoperability and DFS growth for underserved markets.",
    "url": "https://www.macmillankeck.pro/wp-content/uploads/2022/03/Bangalink_briefing_paper_to_BB_161004.pdf",
    "year": "2016"
  },
  {
    "title": "Drafting Malawi’s Data Protection Bill",
    "summary": "Blueprint for pragmatic data protection in low-income economies with limited capacity.",
    "url": "https://www.macmillankeck.pro/wp-content/uploads/2022/03/ABA_Big_Data_Task_Force_white_paper_Part_Two_final_215_Rory_Macmillan_2021_02.pdf",
    "year": "2021"
  },
  {
    "title": "Telecom Dispute Resolution in Emerging Markets",
    "summary": "World Bank / ITU toolkit for arbitration and mediation in telecom sectors.",
    "url": "https://www.macmillankeck.pro/wp-content/uploads/2022/03/1a-Dispute-resolution-in-Indias-telecom-sector.pdf",
    "year": "2009"
  }
]

